{
   "filenameHint" : "24년_11월_2주차.xlsx",
   "gpRevenueTop10" : [
      {
         "company" : "NCSOFT",
         "game" : "리니지M",
         "rank" : 1,
         "rankChange" : "▲1",
         "revenueChangePct" : -23.24,
         "revenueUsd" : 6748444
      },
      {
         "company" : "Onefun",
         "game" : "라스트 워: 서바이벌",
         "rank" : 2,
         "rankChange" : "▼1",
         "revenueChangePct" : -38.51,
         "revenueUsd" : 5691458
      },
      {
         "company" : "Tencent",
         "game" : "승리의 여신: 니케",
         "rank" : 3,
         "rankChange" : "▲11",
         "revenueChangePct" : 266.68,
         "revenueUsd" : 3331519
      },
      {
         "company" : "Kakao",
         "game" : "오딘: 발할라 라이징",
         "rank" : 4,
         "rankChange" : "-",
         "revenueChangePct" : -35.58,
         "revenueUsd" : 2271647
      },
      {
         "company" : "Century Games",
         "game" : "WOS: 화이트아웃 서바이벌",
         "rank" : 5,
         "rankChange" : "▼2",
         "revenueChangePct" : -49.12,
         "revenueUsd" : 1834032
      },
      {
         "company" : "NCSOFT",
         "game" : "리니지2M",
         "rank" : 6,
         "rankChange" : "-",
         "revenueChangePct" : -43.22,
         "revenueUsd" : 1492388
      },
      {
         "company" : "Dream Games",
         "game" : "로얄 매치",
         "rank" : 7,
         "rankChange" : "▼2",
         "revenueChangePct" : -45.59,
         "revenueUsd" : 1450806
      },
      {
         "company" : "Habby",
         "game" : "카피바라 Go!",
         "rank" : 8,
         "rankChange" : "▲4",
         "revenueChangePct" : 7.3,
         "revenueUsd" : 1404885
      },
      {
         "company" : "NCSOFT",
         "game" : "리니지W",
         "rank" : 9,
         "rankChange" : "▼2",
         "revenueChangePct" : -41.67,
         "revenueUsd" : 1128496
      },
      {
         "company" : "NHN",
         "game" : "한게임포커 클래식 with PC",
         "rank" : 10,
         "rankChange" : "▲37",
         "revenueChangePct" : 345.52,
         "revenueUsd" : 1106024
      }
   ],
   "truePeriod" : {
      "endDate" : "2024-11-09",
      "month" : 11,
      "startDate" : "2024-11-03",
      "week" : 1,
      "year" : 2024
   }
}
